setup.cfg
setup.py
pytrapi/__init__.py
pytrapi.egg-info/PKG-INFO
pytrapi.egg-info/SOURCES.txt
pytrapi.egg-info/dependency_links.txt
pytrapi.egg-info/top_level.txt