Metadata-Version: 1.0
Name: pytrapi
Version: 0.1.0
Summary: interface for toontown rewritten's web api
Home-page: https://git.hammerle.me/fphammerle/pytrapi
Author: Fabian Peter Hammerle
Author-email: fabian.hammerle@gmail.com
License: UNKNOWN
Keywords: game,api,toontown rewritten,ttr
Platform: UNKNOWN
